pygeist_client/__init__.py
pygeist_client/_adapter.so
pygeist_client/client.py
pygeist_client/exceptions.py
pygeist_client/response.py
pygeist_client/unrequested.py
pygeist_client/abstract/methods_handler.py
pygeist_client-0.0.2.dist-info/licenses/LICENSE
pygeist_client-0.0.2.dist-info/METADATA
pygeist_client-0.0.2.dist-info/WHEEL
pygeist_client-0.0.2.dist-info/top_level.txt
pygeist_client-0.0.2.dist-info/RECORD
